beam_frequency/__init__.py
beam_frequency/beam_frequency.py
beam_frequency-0.0.2.dist-info/LICENSE
beam_frequency-0.0.2.dist-info/METADATA
beam_frequency-0.0.2.dist-info/WHEEL
beam_frequency-0.0.2.dist-info/top_level.txt
beam_frequency-0.0.2.dist-info/RECORD
